matops/__init__.py
matops/exceptions.py
matops/matrix.py
matops-0.1.4.dist-info/LICENSE
matops-0.1.4.dist-info/WHEEL
matops-0.1.4.dist-info/METADATA
matops-0.1.4.dist-info/RECORD
