Metadata-Version: 2.1
Name: matops
Version: 0.1.4
Summary: Matrix Operations
Author-email: Sarmad Gulzar <sarmadgulzar@hotmail.com>
Classifier: License :: OSI Approved :: MIT License
Project-URL: Home, https://github.com/matops/matops-python
